README.rst
enviro.py
enviro_ipy_ext.py
setup.py
enviro.egg-info/PKG-INFO
enviro.egg-info/SOURCES.txt
enviro.egg-info/dependency_links.txt
enviro.egg-info/not-zip-safe
enviro.egg-info/requires.txt
enviro.egg-info/top_level.txt