Metadata-Version: 1.0
Name: enviro
Version: 0.0.2
Summary: Simple configuration of OS environment variables
Home-page: https://github.com/jwass/enviro
Author: Jacob Wasserman
Author-email: jwasserman@gmail.com
License: MIT
Platform: UNKNOWN
